js.fontawesome-5.0.6-py2.7-nspkg.pth
js/fontawesome/__init__.py
js/fontawesome/test_font_awesome.rst
js/fontawesome/resources/css/fa-brands.css
js/fontawesome/resources/css/fa-brands.min.css
js/fontawesome/resources/css/fa-regular.css
js/fontawesome/resources/css/fa-regular.min.css
js/fontawesome/resources/css/fa-solid.css
js/fontawesome/resources/css/fa-solid.min.css
js/fontawesome/resources/css/fa-svg-with-js.css
js/fontawesome/resources/css/fa-svg-with-js.min.css
js/fontawesome/resources/css/fontawesome-all.css
js/fontawesome/resources/css/fontawesome-all.min.css
js/fontawesome/resources/css/fontawesome.css
js/fontawesome/resources/css/fontawesome.min.css
js/fontawesome/resources/js/fa-brands.js
js/fontawesome/resources/js/fa-brands.min.js
js/fontawesome/resources/js/fa-regular.js
js/fontawesome/resources/js/fa-regular.min.js
js/fontawesome/resources/js/fa-solid.js
js/fontawesome/resources/js/fa-solid.min.js
js/fontawesome/resources/js/fa-v4-shims.js
js/fontawesome/resources/js/fa-v4-shims.min.js
js/fontawesome/resources/js/fontawesome-all.js
js/fontawesome/resources/js/fontawesome-all.min.js
js/fontawesome/resources/js/fontawesome.js
js/fontawesome/resources/js/fontawesome.min.js
js/fontawesome/resources/sprites/fa-brands.svg
js/fontawesome/resources/sprites/fa-regular.svg
js/fontawesome/resources/sprites/fa-solid.svg
js/fontawesome/resources/webfonts/fa-brands-400.eot
js/fontawesome/resources/webfonts/fa-brands-400.svg
js/fontawesome/resources/webfonts/fa-brands-400.ttf
js/fontawesome/resources/webfonts/fa-brands-400.woff
js/fontawesome/resources/webfonts/fa-brands-400.woff2
js/fontawesome/resources/webfonts/fa-regular-400.eot
js/fontawesome/resources/webfonts/fa-regular-400.svg
js/fontawesome/resources/webfonts/fa-regular-400.ttf
js/fontawesome/resources/webfonts/fa-regular-400.woff
js/fontawesome/resources/webfonts/fa-regular-400.woff2
js/fontawesome/resources/webfonts/fa-solid-900.eot
js.fontawesome-5.0.6.dist-info/DESCRIPTION.rst
js.fontawesome-5.0.6.dist-info/METADATA
js.fontawesome-5.0.6.dist-info/RECORD
js.fontawesome-5.0.6.dist-info/WHEEL
js.fontawesome-5.0.6.dist-info/entry_points.txt
js.fontawesome-5.0.6.dist-info/metadata.json
js.fontawesome-5.0.6.dist-info/namespace_packages.txt
js.fontawesome-5.0.6.dist-info/top_level.txt
