Metadata-Version: 1.1
Name: js.fontawesome
Version: 5.0.6
Summary: Fanstatic packaging of Font Awesome
Home-page: https://bitbucket.org/fanstatic/js.fontawesome
Author: Fanstatic Developers
Author-email: fanstatic@googlegroups.com
License: BSD
Keywords: Font Awesome fanstatic WSGI middleware static asset
Platform: UNKNOWN
Classifier: Development Status :: 6 - Mature
Classifier: Environment :: Web Environment
Classifier: Intended Audience :: Developers
Classifier: License :: OSI Approved :: BSD License
Classifier: Natural Language :: English
Classifier: Operating System :: OS Independent
Classifier: Programming Language :: Python :: 2
Classifier: Programming Language :: Python :: 2.7
Classifier: Programming Language :: Python :: 3
Classifier: Programming Language :: Python :: 3.4
Classifier: Programming Language :: Python :: 3.5
Classifier: Programming Language :: Python :: 3.6
Classifier: Programming Language :: Python :: 3.7
Classifier: Topic :: Internet :: WWW/HTTP :: WSGI
Classifier: Topic :: Software Development :: Libraries :: Application Frameworks
